{
  "country": "KR",
  "countryName": "대한민국",
  "version": 5,
  "region": "대전",
  "start_lat": 35.9,
  "start_lng": 127.0,
  "end_lat": 36.7,
  "end_lng": 127.7,
  "type": "radio",
  "stationList": [
    {
      "name": "KBS 대전 1FM",
      "broadcaster": "KBS",
      "frequency": "",
      "url": "https://cfpwwwapi.kbs.co.kr/api/v1/landing/live/channel_code/60_21",
      "streamType": "fetchJson",
      "jsonPath": "channel_item.0.service_url"
    },
    {
      "name": "KBS 대전 해피FM",
      "broadcaster": "KBS",
      "frequency": "",
      "url": "https://cfpwwwapi.kbs.co.kr/api/v1/landing/live/channel_code/60_22",
      "streamType": "fetchJson",
      "jsonPath": "channel_item.0.service_url"
    },
    {
      "name": "KBS 대전 클래식FM",
      "broadcaster": "KBS",
      "frequency": "",
      "url": "https://cfpwwwapi.kbs.co.kr/api/v1/landing/live/channel_code/60_24",
      "streamType": "fetchJson",
      "jsonPath": "channel_item.0.service_url"
    },
    {
      "name": "대전MBC 표준FM",
      "broadcaster": "대전MBC",
      "frequency": "",
      "logo": "kr.mbc",
      "url": "https://ns1.tjmbc.co.kr/live_am/live_am.stream/playlist.m3u8",
      "streamType": "direct"
    },
    {
      "name": "대전MBC FM4U",
      "broadcaster": "대전MBC",
      "frequency": "",
      "logo": "kr.mbc",
      "url": "https://ns1.tjmbc.co.kr/live_fm/live_fm.stream/playlist.m3u8",
      "streamType": "direct"
    },
    {
      "name": "TJB 파워FM",
      "broadcaster": "TJB",
      "frequency": "FM 95.7MHz",
      "logo": "kr.tjb",
      "url": "https://ns1.tjmbc.co.kr/live_fm/live_fm.stream/playlist.m3u8",
      "streamType": "direct"
    },
    {
      "name": "TBN 교통방송 (대전)",
      "broadcaster": "TBN 교통방송",
      "frequency": "FM",
      "url": "https://www.tbn.it.kr/daejeon/myStream/playlist.m3u8",
      "streamType": "direct"
    },
    {
      "name": "국악방송 (대전)",
      "broadcaster": "국악방송",
      "frequency": "FM 99.3MHz(영동), 90.5MHz(대전/세종), 101.7MHz(충주), 90.1MHz(제천/단양), 107.5MHz(청주),  ",
      "url": "https://mgugaklive.nowcdn.co.kr/gugakdaejeon/Daejeonradio.stream/playlist.m3u8",
      "streamType": "direct",
      "metaUrl": "https://new.igbf.kr/api/v1/radio/summary",
      "metaType": "igbf"
    },
    {
      "name": "극동방송 (대전)",
      "broadcaster": "FEBC 극동방송",
      "frequency": "FM 93.3MHz",
      "url": "https://mlive3.febc.net/live5/djlive/playlist.m3u8",
      "streamType": "direct",
      "metaUrl": "https://gangwon.febc.net/api/stream/current?channelId=1223",
      "metaType": "febc"
    },
    {
      "name": "한밭FM",
      "broadcaster": "한밭생활문화방송",
      "frequency": "FM 93.7MHz",
      "logo": "kr.hanbat",
      "url": "http://115.68.194.186:8000/hanbatfm",
      "streamType": "direct"
    }
  ]
}
