{
  "country": "JA",
  "countryName": "일본",
  "version": 1,
  "stationList": [
    {
      "name": "NHK WORLD JAPAN",
      "broadcaster": "NHK",
      "frequency": "",
      "logo": "ja.nhk_world",
      "url": "https://master.nhkworld.jp/nhkworld-radio/playlist/rs1/live.m3u8",
      "streamType": "direct"
    },
    {
      "name": "湘南ビーチFM",
      "broadcaster": "Shonan Beach FM",
      "frequency": "78.9MHz FM",
      "logo": "ja.shownan_beach",
      "url": "https://shonanbeachfm.out.airtime.pro:8000/shonanbeachfm_a",
      "streamType": "direct"
    }
  ]
}
